env.py
ezenv-0.92.dist-info/LICENSE
ezenv-0.92.dist-info/METADATA
ezenv-0.92.dist-info/WHEEL
ezenv-0.92.dist-info/top_level.txt
ezenv-0.92.dist-info/RECORD
